{"id": 203, "label": 2, "grid": [[0, 0, 0, 0, 0, 0, 0, 0, 0, 0, 0, 0], [0, 0, 0, 0, 0, 0, 0, 0, 0, 0, 0, 0], [0, 0, 0, 0, 0, 1, 1, 1, 0, 0, 0, 0], [0, 0, 0, 1, 1, 1, 1, 1, 1, 0, 0, 0], [0, 0, 0, 1, 1, 1, 0, 1, 1, 0, 0, 0], [0, 0, 0, 1, 0, 0, 0, 1, 1, 0, 0, 0], [0, 0, 0, 0, 0, 0, 1, 1, 0, 0, 0, 0], [0, 0, 0, 0, 0, 1, 1, 1, 0, 0, 0, 0], [0, 0, 0, 1, 1, 1, 1, 1, 1, 0, 0, 0], [0, 0, 0, 1, 1, 1, 1, 1, 1, 1, 0, 0], [0, 0, 0, 0, 0, 0, 0, 0, 0, 0, 0, 0], [0, 0, 0, 0, 0, 0, 0, 0, 0, 0, 0, 0]], "row_constraints": [[], [], [3], [6], [3, 2], [1, 2], [2], [3], [6], [7], [], []], "col_constraints": [[], [], [], [3, 2], [2, 2], [3, 3], [2, 4], [8], [3, 2], [1], [], []]}